HISTORY.rst
README.rst
bootstrap.py
buildout.cfg
setup.py
mr/__init__.py
mr.awsome.egg-info/PKG-INFO
mr.awsome.egg-info/SOURCES.txt
mr.awsome.egg-info/dependency_links.txt
mr.awsome.egg-info/entry_points.txt
mr.awsome.egg-info/namespace_packages.txt
mr.awsome.egg-info/not-zip-safe
mr.awsome.egg-info/requires.txt
mr.awsome.egg-info/top_level.txt
mr/awsome/__init__.py
mr/awsome/common.py
mr/awsome/config.py
mr/awsome/ec2.py
mr/awsome/fabric_integration.py
mr/awsome/plain.py
mr/awsome/template.py
mr/awsome/tests/__init__.py
mr/awsome/tests/dummy_plugin.py
mr/awsome/tests/test_awsome.py
mr/awsome/tests/test_common.py
mr/awsome/tests/test_config.py
mr/awsome/tests/test_ec2.py
mr/awsome/tests/test_plain.py
mr/awsome/tests/test_template.py