Metadata-Version: 1.0
Name: mr.awsome
Version: 0.12
Summary: A script allowing to setup Amazon EC2 instances through configuration files.
Home-page: http://github.com/fschulze/mr.awsome
Author: Florian Schulze
Author-email: florian.schulze@gmx.net
License: UNKNOWN
Platform: UNKNOWN
